odoo/addons/delivery_carrier_label_paazl/README.rst
odoo/addons/delivery_carrier_label_paazl/__init__.py
odoo/addons/delivery_carrier_label_paazl/__manifest__.py
odoo/addons/delivery_carrier_label_paazl/controllers/__init__.py
odoo/addons/delivery_carrier_label_paazl/controllers/main.py
odoo/addons/delivery_carrier_label_paazl/data/delivery_carrier.xml
odoo/addons/delivery_carrier_label_paazl/data/delivery_carrier_template_option.xml
odoo/addons/delivery_carrier_label_paazl/data/ir_config_parameter.xml
odoo/addons/delivery_carrier_label_paazl/i18n/.empty
odoo/addons/delivery_carrier_label_paazl/i18n/delivery_carrier_label_paazl.pot
odoo/addons/delivery_carrier_label_paazl/models/__init__.py
odoo/addons/delivery_carrier_label_paazl/models/carrier_account.py
odoo/addons/delivery_carrier_label_paazl/models/delivery_carrier.py
odoo/addons/delivery_carrier_label_paazl/models/stock_picking.py
odoo/addons/delivery_carrier_label_paazl/readme/CONFIGURE.rst
odoo/addons/delivery_carrier_label_paazl/readme/CONTRIBUTORS.rst
odoo/addons/delivery_carrier_label_paazl/readme/DESCRIPTION.rst
odoo/addons/delivery_carrier_label_paazl/readme/USAGE.rst
odoo/addons/delivery_carrier_label_paazl/readme/newsfragments/.gitkeep
odoo/addons/delivery_carrier_label_paazl/static/description/icon.png
odoo/addons/delivery_carrier_label_paazl/static/description/index.html
odoo/addons/delivery_carrier_label_paazl/tests/__init__.py
odoo/addons/delivery_carrier_label_paazl/tests/test_delivery_carrier_label_paazl.py
odoo/addons/delivery_carrier_label_paazl/views/carrier_account.xml
odoo12_addon_delivery_carrier_label_paazl-12.0.1.3.0.dist-info/METADATA
odoo12_addon_delivery_carrier_label_paazl-12.0.1.3.0.dist-info/WHEEL
odoo12_addon_delivery_carrier_label_paazl-12.0.1.3.0.dist-info/top_level.txt
odoo12_addon_delivery_carrier_label_paazl-12.0.1.3.0.dist-info/RECORD
